setup.py
SqlAlchemyPackages.egg-info/PKG-INFO
SqlAlchemyPackages.egg-info/SOURCES.txt
SqlAlchemyPackages.egg-info/dependency_links.txt
SqlAlchemyPackages.egg-info/top_level.txt
SqlalchemyPackages/__init__.py
SqlalchemyPackages/Engine/Devices.py
SqlalchemyPackages/Engine/Samples.py
SqlalchemyPackages/Engine/__init__.py
SqlalchemyPackages/Engine/Entities/__init__.py
SqlalchemyPackages/Engine/Entities/users.py