Metadata-Version: 1.0
Name: SqlAlchemyPackages
Version: 0.0.1
Summary: Packages SqlAlchemy for using easily
Home-page: UNKNOWN
Author: yitakabe
Author-email: yitakabe@gmail.com
License: MIT License
Keywords: simple,test
Platform: any
